{
    "info": {
        "_postman_id": "b3fd4c22-7777-4444-8888-51f3b3b4a2d1",
        "name": "Auth System API",
        "description": "Collection for User Authentication and Authorization System",
        "schema": "https://schema.getpostman.com/json/collection/v2.1.0/collection.json"
    },
    "item": [
        {
            "name": "Auth & Public",
            "item": [
                {
                    "name": "Register User",
                    "request": {
                        "method": "POST",
                        "header": [],
                        "body": {
                            "mode": "raw",
                            "raw": "{\n    \"username\": \"testuser\",\n    \"email\": \"test@example.com\",\n    \"password\": \"password123\"\n}",
                            "options": {
                                "raw": {
                                    "language": "json"
                                }
                            }
                        },
                        "url": {
                            "raw": "{{baseUrl}}/api/users/register",
                            "host": [
                                "{{baseUrl}}"
                            ],
                            "path": [
                                "api",
                                "users",
                                "register"
                            ]
                        }
                    },
                    "response": []
                },
                {
                    "name": "Login",
                    "event": [
                        {
                            "listen": "test",
                            "script": {
                                "exec": [
                                    "var jsonData = pm.response.json();",
                                    "if (jsonData.data && jsonData.data.token) {",
                                    "    pm.environment.set(\"authToken\", jsonData.data.token);",
                                    "    console.log(\"Token saved to environment variable 'authToken'\");",
                                    "}"
                                ],
                                "type": "text/javascript"
                            }
                        }
                    ],
                    "request": {
                        "method": "POST",
                        "header": [],
                        "body": {
                            "mode": "raw",
                            "raw": "{\n    \"usernameOrEmail\": \"testuser\",\n    \"password\": \"password123\"\n}",
                            "options": {
                                "raw": {
                                    "language": "json"
                                }
                            }
                        },
                        "url": {
                            "raw": "{{baseUrl}}/api/auth/login",
                            "host": [
                                "{{baseUrl}}"
                            ],
                            "path": [
                                "api",
                                "auth",
                                "login"
                            ]
                        }
                    },
                    "response": []
                },
                {
                    "name": "Forgot Password",
                    "request": {
                        "method": "POST",
                        "header": [],
                        "body": {
                            "mode": "raw",
                            "raw": "{\n    \"email\": \"test@example.com\"\n}",
                            "options": {
                                "raw": {
                                    "language": "json"
                                }
                            }
                        },
                        "url": {
                            "raw": "{{baseUrl}}/api/auth/forgot-password",
                            "host": [
                                "{{baseUrl}}"
                            ],
                            "path": [
                                "api",
                                "auth",
                                "forgot-password"
                            ]
                        }
                    },
                    "response": []
                },
                {
                    "name": "Validate OTP",
                    "request": {
                        "method": "POST",
                        "header": [],
                        "body": {
                            "mode": "raw",
                            "raw": "{\n    \"email\": \"test@example.com\",\n    \"otp\": \"123456\"\n}",
                            "options": {
                                "raw": {
                                    "language": "json"
                                }
                            }
                        },
                        "url": {
                            "raw": "{{baseUrl}}/api/auth/validate-otp",
                            "host": [
                                "{{baseUrl}}"
                            ],
                            "path": [
                                "api",
                                "auth",
                                "validate-otp"
                            ]
                        }
                    },
                    "response": []
                },
                {
                    "name": "Reset Password",
                    "request": {
                        "method": "POST",
                        "header": [],
                        "body": {
                            "mode": "raw",
                            "raw": "{\n    \"email\": \"test@example.com\",\n    \"otp\": \"123456\",\n    \"newPassword\": \"newPassword123\"\n}",
                            "options": {
                                "raw": {
                                    "language": "json"
                                }
                            }
                        },
                        "url": {
                            "raw": "{{baseUrl}}/api/auth/reset-password",
                            "host": [
                                "{{baseUrl}}"
                            ],
                            "path": [
                                "api",
                                "auth",
                                "reset-password"
                            ]
                        }
                    },
                    "response": []
                }
            ]
        },
        {
            "name": "Current User (Me)",
            "item": [
                {
                    "name": "Get Profile",
                    "request": {
                        "auth": {
                            "type": "bearer",
                            "bearer": [
                                {
                                    "key": "token",
                                    "value": "{{authToken}}",
                                    "type": "string"
                                }
                            ]
                        },
                        "method": "GET",
                        "header": [],
                        "url": {
                            "raw": "{{baseUrl}}/api/users/me",
                            "host": [
                                "{{baseUrl}}"
                            ],
                            "path": [
                                "api",
                                "users",
                                "me"
                            ]
                        }
                    },
                    "response": []
                },
                {
                    "name": "Update Profile (PUT)",
                    "request": {
                        "auth": {
                            "type": "bearer",
                            "bearer": [
                                {
                                    "key": "token",
                                    "value": "{{authToken}}",
                                    "type": "string"
                                }
                            ]
                        },
                        "method": "PUT",
                        "header": [],
                        "body": {
                            "mode": "raw",
                            "raw": "{\n    \"username\": \"updatedUser\",\n    \"email\": \"updated@example.com\"\n}",
                            "options": {
                                "raw": {
                                    "language": "json"
                                }
                            }
                        },
                        "url": {
                            "raw": "{{baseUrl}}/api/users/me",
                            "host": [
                                "{{baseUrl}}"
                            ],
                            "path": [
                                "api",
                                "users",
                                "me"
                            ]
                        }
                    },
                    "response": []
                },
                {
                    "name": "Patch Profile (PATCH)",
                    "request": {
                        "auth": {
                            "type": "bearer",
                            "bearer": [
                                {
                                    "key": "token",
                                    "value": "{{authToken}}",
                                    "type": "string"
                                }
                            ]
                        },
                        "method": "PATCH",
                        "header": [],
                        "body": {
                            "mode": "raw",
                            "raw": "{\n    \"username\": \"patchedUser\"\n}",
                            "options": {
                                "raw": {
                                    "language": "json"
                                }
                            }
                        },
                        "url": {
                            "raw": "{{baseUrl}}/api/users/me",
                            "host": [
                                "{{baseUrl}}"
                            ],
                            "path": [
                                "api",
                                "users",
                                "me"
                            ]
                        }
                    },
                    "response": []
                }
            ]
        },
        {
            "name": "Admin Management",
            "item": [
                {
                    "name": "Get All Users",
                    "request": {
                        "auth": {
                            "type": "bearer",
                            "bearer": [
                                {
                                    "key": "token",
                                    "value": "{{authToken}}",
                                    "type": "string"
                                }
                            ]
                        },
                        "method": "GET",
                        "header": [],
                        "url": {
                            "raw": "{{baseUrl}}/api/users",
                            "host": [
                                "{{baseUrl}}"
                            ],
                            "path": [
                                "api",
                                "users"
                            ]
                        }
                    },
                    "response": []
                },
                {
                    "name": "Disable User",
                    "request": {
                        "auth": {
                            "type": "bearer",
                            "bearer": [
                                {
                                    "key": "token",
                                    "value": "{{authToken}}",
                                    "type": "string"
                                }
                            ]
                        },
                        "method": "PATCH",
                        "header": [],
                        "url": {
                            "raw": "{{baseUrl}}/api/users/1/disable",
                            "host": [
                                "{{baseUrl}}"
                            ],
                            "path": [
                                "api",
                                "users",
                                "1",
                                "disable"
                            ]
                        }
                    },
                    "response": []
                },
                {
                    "name": "Update User (Admin)",
                    "request": {
                        "auth": {
                            "type": "bearer",
                            "bearer": [
                                {
                                    "key": "token",
                                    "value": "{{authToken}}",
                                    "type": "string"
                                }
                            ]
                        },
                        "method": "PUT",
                        "header": [],
                        "body": {
                            "mode": "raw",
                            "raw": "{\n    \"username\": \"adminUpdated\",\n    \"email\": \"admin@updated.com\"\n}",
                            "options": {
                                "raw": {
                                    "language": "json"
                                }
                            }
                        },
                        "url": {
                            "raw": "{{baseUrl}}/api/users/1",
                            "host": [
                                "{{baseUrl}}"
                            ],
                            "path": [
                                "api",
                                "users",
                                "1"
                            ]
                        }
                    },
                    "response": []
                },
                {
                    "name": "Delete User",
                    "request": {
                        "auth": {
                            "type": "bearer",
                            "bearer": [
                                {
                                    "key": "token",
                                    "value": "{{authToken}}",
                                    "type": "string"
                                }
                            ]
                        },
                        "method": "DELETE",
                        "header": [],
                        "url": {
                            "raw": "{{baseUrl}}/api/users/1",
                            "host": [
                                "{{baseUrl}}"
                            ],
                            "path": [
                                "api",
                                "users",
                                "1"
                            ]
                        }
                    },
                    "response": []
                }
            ]
        }
    ],
    "variable": [
        {
            "key": "baseUrl",
            "value": "http://localhost:8080",
            "type": "string"
        }
    ]
}